django_sql_queries/__init__.py
django_sql_queries/middleware.py
django_sql_queries-1.0.1.dist-info/METADATA
django_sql_queries-1.0.1.dist-info/WHEEL
django_sql_queries-1.0.1.dist-info/top_level.txt
django_sql_queries-1.0.1.dist-info/RECORD
